LICENSE
MANIFEST.in
README.rst
setup.py
simpleui/__init__.py
simpleui/admin.py
simpleui/apps.py
simpleui/forms.py
simpleui/widgets.py
simpleui/__pycache__/__init__.cpython-39.pyc
simpleui/locale/zh_Hans/LC_MESSAGES/django.mo
simpleui/locale/zh_Hans/LC_MESSAGES/django.po
simpleui/locale/zh_Hans/LC_MESSAGES/make.sh
simpleui/static/admin/simpleui-x/automatic/dicts.js
simpleui/static/admin/simpleui-x/automatic/segment.js
simpleui/static/admin/simpleui-x/css/base.css
simpleui/static/admin/simpleui-x/css/base.css.map
simpleui/static/admin/simpleui-x/css/base.less
simpleui/static/admin/simpleui-x/css/index.css
simpleui/static/admin/simpleui-x/css/index.css.map
simpleui/static/admin/simpleui-x/css/index.less
simpleui/static/admin/simpleui-x/css/login.css
simpleui/static/admin/simpleui-x/elementui/index.js
simpleui/static/admin/simpleui-x/elementui/locale/format.js
simpleui/static/admin/simpleui-x/elementui/locale/index.js
simpleui/static/admin/simpleui-x/elementui/locale/lang/af-ZA.js
simpleui/static/admin/simpleui-x/elementui/locale/lang/ar.js
simpleui/static/admin/simpleui-x/elementui/locale/lang/bg.js
simpleui/static/admin/simpleui-x/elementui/locale/lang/ca.js
simpleui/static/admin/simpleui-x/elementui/locale/lang/cs-CZ.js
simpleui/static/admin/simpleui-x/elementui/locale/lang/da.js
simpleui/static/admin/simpleui-x/elementui/locale/lang/de.js
simpleui/static/admin/simpleui-x/elementui/locale/lang/ee.js
simpleui/static/admin/simpleui-x/elementui/locale/lang/el.js
simpleui/static/admin/simpleui-x/elementui/locale/lang/en.js
simpleui/static/admin/simpleui-x/elementui/locale/lang/eo.js
simpleui/static/admin/simpleui-x/elementui/locale/lang/es.js
simpleui/static/admin/simpleui-x/elementui/locale/lang/eu.js
simpleui/static/admin/simpleui-x/elementui/locale/lang/fa.js
simpleui/static/admin/simpleui-x/elementui/locale/lang/fi.js
simpleui/static/admin/simpleui-x/elementui/locale/lang/fr.js
simpleui/static/admin/simpleui-x/elementui/locale/lang/he.js
simpleui_admin.egg-info/PKG-INFO
simpleui_admin.egg-info/SOURCES.txt
simpleui_admin.egg-info/dependency_links.txt
simpleui_admin.egg-info/not-zip-safe
simpleui_admin.egg-info/requires.txt
simpleui_admin.egg-info/top_level.txt