Metadata-Version: 2.1
Name: simpleui-admin
Version: 2023.6.12.1
Summary: django admin theme 后台模板,后台需求定制化
Home-page: https://github.com/RelaxedDong/simpleui
Author: donghao
Author-email: 1417766861@qq.com
License: Apache License 2.0
Platform: UNKNOWN
Classifier: Programming Language :: Python :: 3
Classifier: Operating System :: OS Independent
License-File: LICENSE
